ys_packet_generator/__init__.py
ys_packet_generator/generator.py
ys_packet_generator/server.py
ys_packet_generator-0.0.3.dist-info/LICENSE
ys_packet_generator-0.0.3.dist-info/METADATA
ys_packet_generator-0.0.3.dist-info/WHEEL
ys_packet_generator-0.0.3.dist-info/top_level.txt
ys_packet_generator-0.0.3.dist-info/RECORD
