Metadata-Version: 2.1
Name: ys-packet-generator
Version: 0.0.3
Summary: Packet Generator
Author-email: Yoni Shpund <shpundyoni@gmail.com>
Project-URL: Homepage, https://github.com/YoniShpund/ys_packet_generator
Project-URL: Bug Tracker, https://github.com/YoniShpund/ys_packet_generator/issues
Classifier: Programming Language :: Python :: 3
Classifier: License :: OSI Approved :: MIT License
Classifier: Operating System :: OS Independent
Requires-Python: >=3.7
License-File: LICENSE
